[
    {"input": "What is the capital of France?", "output": "The capital of France is Paris."},
    {"input": "Who wrote '1984'?", "output": "George Orwell wrote '1984'."},
    {"input": "What is the largest planet in our solar system?", "output": "Jupiter is the largest planet in our solar system."},
    {"input": "Who painted the Mona Lisa?", "output": "Leonardo da Vinci painted the Mona Lisa."},
    {"input": "What is the chemical symbol for gold?", "output": "The chemical symbol for gold is Au."},
    {"input": "What year did World War II end?", "output": "World War II ended in 1945."},
    {"input": "Who invented the telephone?", "output": "Alexander Graham Bell invented the telephone."},
    {"input": "What is the tallest mountain in the world?", "output": "Mount Everest is the tallest mountain in the world."},
    {"input": "What is the speed of light?", "output": "The speed of light is approximately 299,792,458 meters per second."},
    {"input": "Who was the first person to walk on the moon?", "output": "Neil Armstrong was the first person to walk on the moon."},
    {"input": "What is the largest ocean on Earth?", "output": "The Pacific Ocean is the largest ocean on Earth."},
    {"input": "Who composed the Ninth Symphony?", "output": "Ludwig van Beethoven composed the Ninth Symphony."},
    {"input": "What is the chemical formula for water?", "output": "The chemical formula for water is H2O."},
    {"input": "Who painted 'The Starry Night'?", "output": "Vincent van Gogh painted 'The Starry Night'."},
    {"input": "What is the capital of Japan?", "output": "The capital of Japan is Tokyo."},
    {"input": "Who wrote 'Romeo and Juliet'?", "output": "William Shakespeare wrote 'Romeo and Juliet'."},
    {"input": "What is the smallest planet in our solar system?", "output": "Mercury is the smallest planet in our solar system."},
    {"input": "What year did the Titanic sink?", "output": "The Titanic sank in 1912."},
    {"input": "Who discovered penicillin?", "output": "Alexander Fleming discovered penicillin."},
    {"input": "What is the longest river in the world?", "output": "The Nile River is the longest river in the world."},
    {"input": "Who was the first President of the United States?", "output": "George Washington was the first President of the United States."},
    {"input": "What is the hardest natural substance on Earth?", "output": "Diamond is the hardest natural substance on Earth."},
    {"input": "Who developed the theory of relativity?", "output": "Albert Einstein developed the theory of relativity."},
    {"input": "What is the capital of Australia?", "output": "The capital of Australia is Canberra."},
    {"input": "Who painted the Sistine Chapel ceiling?", "output": "Michelangelo painted the Sistine Chapel ceiling."},
    {"input": "What is the largest desert in the world?", "output": "The Antarctic Desert is the largest desert in the world."},
    {"input": "Who invented the light bulb?", "output": "Thomas Edison invented the practical electric light bulb."},
    {"input": "What is the boiling point of water?", "output": "Water boils at 100 degrees Celsius at sea level."},
    {"input": "Who wrote 'Don Quixote'?", "output": "Miguel de Cervantes wrote 'Don Quixote'."},
    {"input": "What is the deepest point in the ocean?", "output": "The Challenger Deep in the Mariana Trench is the deepest point in the ocean."},
    {"input": "Who discovered gravity?", "output": "Sir Isaac Newton discovered and described the law of gravity."},
    {"input": "What is the largest mammal on Earth?", "output": "The Blue Whale is the largest mammal on Earth."},
    {"input": "Who painted 'The Last Supper'?", "output": "Leonardo da Vinci painted 'The Last Supper'."},
    {"input": "What is the capital of Brazil?", "output": "The capital of Brazil is Brasília."},
    {"input": "Who wrote 'The Great Gatsby'?", "output": "F. Scott Fitzgerald wrote 'The Great Gatsby'."},
    {"input": "What is the most abundant element in the universe?", "output": "Hydrogen is the most abundant element in the universe."},
    {"input": "Who invented the World Wide Web?", "output": "Tim Berners-Lee invented the World Wide Web."},
    {"input": "What is the fastest land animal?", "output": "The cheetah is the fastest land animal."},
    {"input": "Who composed 'The Four Seasons'?", "output": "Antonio Vivaldi composed 'The Four Seasons'."},
    {"input": "What is the capital of China?", "output": "The capital of China is Beijing."},
    {"input": "Who discovered America?", "output": "Christopher Columbus is traditionally credited with discovering America in 1492."},
    {"input": "What is the largest bird in the world?", "output": "The ostrich is the largest bird in the world."},
    {"input": "Who invented the steam engine?", "output": "James Watt significantly improved and developed the modern steam engine."},
    {"input": "What is the smallest country in the world?", "output": "Vatican City is the smallest country in the world."},
    {"input": "Who wrote 'War and Peace'?", "output": "Leo Tolstoy wrote 'War and Peace'."},
    {"input": "What is the most common blood type?", "output": "Type O+ is the most common blood type."},
    {"input": "Who founded Microsoft?", "output": "Bill Gates and Paul Allen founded Microsoft."},
    {"input": "What is the largest organ in the human body?", "output": "The skin is the largest organ in the human body."},
    {"input": "Who was the first woman in space?", "output": "Valentina Tereshkova was the first woman in space."},
    {"input": "What is the currency of Japan?", "output": "The currency of Japan is the Yen."}
]